[
{"name":"producing","ph":"B","ts":1807894067,"pid":1,"tid":1},
{"name":"sem_wait_blocking","ph":"B","ts":1807894126,"pid":1,"tid":2},
{"name":"producing","ph":"E","ts":1807897195,"pid":1,"tid":1},
{"name":"sem_post","ph":"B","ts":1807897197,"pid":1,"tid":1},
{"name":"sem_wait_blocking","ph":"E","ts":1807897219,"pid":1,"tid":2},
{"name":"consuming","ph":"B","ts":1807897219,"pid":1,"tid":2},
{"name":"sem_post","ph":"E","ts":1807897296,"pid":1,"tid":1},
{"name":"consuming","ph":"E","ts":1807898615,"pid":1,"tid":2},
{"name":"sem_wait_blocking","ph":"B","ts":1807898617,"pid":1,"tid":2},
{"name":"producing","ph":"B","ts":1807899382,"pid":1,"tid":1},
{"name":"producing","ph":"E","ts":1807902607,"pid":1,"tid":1},
{"name":"sem_post","ph":"B","ts":1807902609,"pid":1,"tid":1},
{"name":"sem_wait_blocking","ph":"E","ts":1807902659,"pid":1,"tid":2},
{"name":"consuming","ph":"B","ts":1807902660,"pid":1,"tid":2},
{"name":"sem_post","ph":"E","ts":1807903135,"pid":1,"tid":1},
{"name":"consuming","ph":"E","ts":1807904271,"pid":1,"tid":2},
{"name":"sem_wait_blocking","ph":"B","ts":1807904273,"pid":1,"tid":2},
{"name":"producing","ph":"B","ts":1807905232,"pid":1,"tid":1},
{"name":"producing","ph":"E","ts":1807908369,"pid":1,"tid":1},
{"name":"sem_post","ph":"B","ts":1807908371,"pid":1,"tid":1},
{"name":"sem_wait_blocking","ph":"E","ts":1807908394,"pid":1,"tid":2},
{"name":"consuming","ph":"B","ts":1807908395,"pid":1,"tid":2},
{"name":"sem_post","ph":"E","ts":1807908531,"pid":1,"tid":1},
{"name":"consuming","ph":"E","ts":1807909908,"pid":1,"tid":2},
{"name":"sem_wait_blocking","ph":"B","ts":1807909910,"pid":1,"tid":2},
{"name":"producing","ph":"B","ts":1807910616,"pid":1,"tid":1},
{"name":"producing","ph":"E","ts":1807913844,"pid":1,"tid":1},
{"name":"sem_post","ph":"B","ts":1807913846,"pid":1,"tid":1},
{"name":"sem_wait_blocking","ph":"E","ts":1807913974,"pid":1,"tid":2},
{"name":"consuming","ph":"B","ts":1807913975,"pid":1,"tid":2},
{"name":"sem_post","ph":"E","ts":1807914065,"pid":1,"tid":1},
{"name":"consuming","ph":"E","ts":1807915176,"pid":1,"tid":2},
{"name":"sem_wait_blocking","ph":"B","ts":1807915178,"pid":1,"tid":2},
{"name":"producing","ph":"B","ts":1807916149,"pid":1,"tid":1},
{"name":"producing","ph":"E","ts":1807919245,"pid":1,"tid":1},
{"name":"sem_post","ph":"B","ts":1807919247,"pid":1,"tid":1},
{"name":"sem_post","ph":"E","ts":1807919260,"pid":1,"tid":1},
{"name":"sem_wait_blocking","ph":"E","ts":1807919293,"pid":1,"tid":2},
{"name":"consuming","ph":"B","ts":1807919294,"pid":1,"tid":2},
{"name":"consuming","ph":"E","ts":1807920383,"pid":1,"tid":2},
{"name":"sem_wait_blocking","ph":"B","ts":1807920385,"pid":1,"tid":2},
{"name":"producing","ph":"B","ts":1807921342,"pid":1,"tid":1},
{"name":"producing","ph":"E","ts":1807924501,"pid":1,"tid":1},
{"name":"sem_post","ph":"B","ts":1807924503,"pid":1,"tid":1},
{"name":"sem_wait_blocking","ph":"E","ts":1807924525,"pid":1,"tid":2},
{"name":"consuming","ph":"B","ts":1807924526,"pid":1,"tid":2},
{"name":"sem_post","ph":"E","ts":1807924764,"pid":1,"tid":1},
{"name":"consuming","ph":"E","ts":1807925932,"pid":1,"tid":2},
{"name":"sem_wait_blocking","ph":"B","ts":1807925934,"pid":1,"tid":2},
{"name":"producing","ph":"B","ts":1807926884,"pid":1,"tid":1},
{"name":"producing","ph":"E","ts":1807930072,"pid":1,"tid":1},
{"name":"sem_post","ph":"B","ts":1807930074,"pid":1,"tid":1},
{"name":"sem_wait_blocking","ph":"E","ts":1807930155,"pid":1,"tid":2},
{"name":"consuming","ph":"B","ts":1807930156,"pid":1,"tid":2},
{"name":"sem_post","ph":"E","ts":1807930300,"pid":1,"tid":1},
{"name":"consuming","ph":"E","ts":1807932074,"pid":1,"tid":2},
{"name":"sem_wait_blocking","ph":"B","ts":1807932076,"pid":1,"tid":2},
{"name":"producing","ph":"B","ts":1807932385,"pid":1,"tid":1},
{"name":"producing","ph":"E","ts":1807935473,"pid":1,"tid":1},
{"name":"sem_post","ph":"B","ts":1807935475,"pid":1,"tid":1},
{"name":"sem_post","ph":"E","ts":1807935487,"pid":1,"tid":1},
{"name":"sem_wait_blocking","ph":"E","ts":1807935596,"pid":1,"tid":2},
{"name":"consuming","ph":"B","ts":1807935597,"pid":1,"tid":2},
{"name":"consuming","ph":"E","ts":1807936688,"pid":1,"tid":2},
{"name":"sem_wait_blocking","ph":"B","ts":1807936862,"pid":1,"tid":2},
{"name":"producing","ph":"B","ts":1807937571,"pid":1,"tid":1},
{"name":"producing","ph":"E","ts":1807941610,"pid":1,"tid":1},
{"name":"sem_post","ph":"B","ts":1807941612,"pid":1,"tid":1},
{"name":"sem_post","ph":"E","ts":1807941628,"pid":1,"tid":1},
{"name":"sem_wait_blocking","ph":"E","ts":1807941634,"pid":1,"tid":2},
{"name":"consuming","ph":"B","ts":1807941635,"pid":1,"tid":2},
{"name":"consuming","ph":"E","ts":1807942729,"pid":1,"tid":2},
{"name":"sem_wait_blocking","ph":"B","ts":1807942731,"pid":1,"tid":2},
{"name":"producing","ph":"B","ts":1807943807,"pid":1,"tid":1},
{"name":"producing","ph":"E","ts":1807946895,"pid":1,"tid":1},
{"name":"sem_post","ph":"B","ts":1807946897,"pid":1,"tid":1},
{"name":"sem_post","ph":"E","ts":1807946913,"pid":1,"tid":1},
{"name":"sem_wait_blocking","ph":"E","ts":1807946919,"pid":1,"tid":2},
{"name":"consuming","ph":"B","ts":1807946920,"pid":1,"tid":2},
{"name":"consuming","ph":"E","ts":1807948047,"pid":1,"tid":2},
{}]
